commanderbot/__init__.py
commanderbot/__main__.py
commanderbot/core/__init__.py
commanderbot/core/application_emoji_manager.py
commanderbot/core/cli.py
commanderbot/core/command_tree.py
commanderbot/core/commander_bot.py
commanderbot/core/config.py
commanderbot/core/configured_extension.py
commanderbot/core/error_handling.py
commanderbot/core/exceptions.py
commanderbot/core/help_command.py
commanderbot/core/logging.py
commanderbot/core/utils.py
commanderbot/ext/__init__.py
commanderbot/ext/allay/__init__.py
commanderbot/ext/allay/allay_cog.py
commanderbot/ext/automod/__init__.py
commanderbot/ext/automod/actions/__init__.py
commanderbot/ext/automod/actions/abc/__init__.py
commanderbot/ext/automod/actions/abc/add_roles_to_target_base.py
commanderbot/ext/automod/actions/abc/remove_roles_from_target_base.py
commanderbot/ext/automod/actions/add_reactions.py
commanderbot/ext/automod/actions/add_roles_to_actor.py
commanderbot/ext/automod/actions/add_roles_to_author.py
commanderbot/ext/automod/actions/add_users_to_thread.py
commanderbot/ext/automod/actions/check_messages.py
commanderbot/ext/automod/actions/delete_message.py
commanderbot/ext/automod/actions/dm_member.py
commanderbot/ext/automod/actions/edit_thread.py
commanderbot/ext/automod/actions/join_thread.py
commanderbot/ext/automod/actions/log_message.py
commanderbot/ext/automod/actions/remove_all_reactions.py
commanderbot/ext/automod/actions/remove_own_reactions.py
commanderbot/ext/automod/actions/remove_reactions.py
commanderbot/ext/automod/actions/remove_roles_from_actor.py
commanderbot/ext/automod/actions/remove_roles_from_author.py
commanderbot/ext/automod/actions/reply_to_message.py
commanderbot/ext/automod/actions/send_message.py
commanderbot/ext/automod/actions/throw_error.py
commanderbot/ext/automod/actions/wait.py
commanderbot/ext/automod/automod_action.py
commanderbot/ext/automod/automod_cog.py
commanderbot/ext/automod/automod_condition.py
commanderbot/ext/automod/automod_data.py
commanderbot-0.22.0.dist-info/WHEEL
commanderbot-0.22.0.dist-info/entry_points.txt
commanderbot-0.22.0.dist-info/METADATA
commanderbot-0.22.0.dist-info/RECORD
