Metadata-Version: 2.3
Name: commanderbot
Version: 0.22.0
Summary: A collection of utilities and extensions for discord.py bots.
Keywords: discord,bot
Author: Ersatz, Arcensoth
Author-email: Ersatz <ersatz0077@gmail.com>, Arcensoth <arcensoth@gmail.com>
License: MIT License
Classifier: Programming Language :: Python :: 3
Classifier: Programming Language :: Python :: 3.14
Classifier: License :: OSI Approved :: MIT License
Requires-Dist: discord-py>=2.6.0
Requires-Dist: python-dotenv>=1.0.0
Requires-Dist: colorama>=0.4.0
Requires-Dist: colorlog>=6.10.0
Requires-Dist: aiosqlite>=0.21.0
Requires-Dist: sqlalchemy>=1.4.0,<2.0.0
Requires-Dist: jsonpath-ng>=1.7.0
Requires-Dist: pyyaml>=6.0.0
Requires-Dist: aiohttp>=3.13.0
Requires-Dist: emoji>=2.0.0
Requires-Dist: allay>=1.3.0
Requires-Dist: mccq>=1.0.0
Requires-Dist: psutil>=7.0.0
Requires-Python: >=3.14, <3.15
Project-URL: Changelog, https://github.com/MinecraftCommands/commanderbot-py/blob/main/CHANGELOG.md
Project-URL: Homepage, https://github.com/MinecraftCommands/commanderbot-py
Project-URL: Repository, https://github.com/MinecraftCommands/commanderbot-py
